iafa/__init__.py
iafa/imageapi.py
FastIIIFimageAPI-0.0.1.dist-info/LICENSE
FastIIIFimageAPI-0.0.1.dist-info/METADATA
FastIIIFimageAPI-0.0.1.dist-info/WHEEL
FastIIIFimageAPI-0.0.1.dist-info/top_level.txt
FastIIIFimageAPI-0.0.1.dist-info/RECORD
