Metadata-Version: 2.1
Name: FastIIIFimageAPI
Version: 0.0.1
Summary: iiif ImageAPI for FastAPI
Home-page: https://github.com/WilhelmWeber/IIIFimageAPIforFastAPI
Download-URL: https://github.com/WilhelmWeber/IIIFimageAPIforFastAPI
Author: Yuto_Takizawa
Author-email: mokoda5243@gmail.com
License: MIT
Keywords: iiif fastapi
Classifier: License :: OSI Approved :: MIT License
Classifier: Programming Language :: Python :: 3.6
License-File: LICENSE
Requires-Dist: pillow >=10.2.0
Requires-Dist: fastapi >=0.104.1
